.gitignore
README.txt
bootstrap.py
setup.cfg
setup.py
test-plone-3.x.cfg
test-plone-4.0.x.cfg
test-plone-4.1.x.cfg
docs/HISTORY.txt
docs/INSTALL.txt
docs/LICENSE.GPL
docs/LICENSE.txt
sc/__init__.py
sc.contentrules.group.egg-info/PKG-INFO
sc.contentrules.group.egg-info/SOURCES.txt
sc.contentrules.group.egg-info/dependency_links.txt
sc.contentrules.group.egg-info/entry_points.txt
sc.contentrules.group.egg-info/namespace_packages.txt
sc.contentrules.group.egg-info/not-zip-safe
sc.contentrules.group.egg-info/requires.txt
sc.contentrules.group.egg-info/top_level.txt
sc/contentrules/__init__.py
sc/contentrules/group/README.txt
sc/contentrules/group/__init__.py
sc/contentrules/group/action.py
sc/contentrules/group/configure.zcml
sc/contentrules/group/interfaces.py
sc/contentrules/group/testing.py
sc/contentrules/group/version.txt
sc/contentrules/group/locales/manual.pot
sc/contentrules/group/locales/rebuildAll.sh
sc/contentrules/group/locales/sc.contentrules.group.pot
sc/contentrules/group/locales/en/LC_MESSAGES/sc.contentrules.group.po
sc/contentrules/group/locales/es/LC_MESSAGES/sc.contentrules.group.po
sc/contentrules/group/locales/pt_BR/LC_MESSAGES/sc.contentrules.group.po
sc/contentrules/group/tests/__init__.py
sc/contentrules/group/tests/test_group.py