Metadata-Version: 1.0
Name: sc.contentrules.group
Version: 0.5
Summary: Plone content rule to create a group based on a content
Home-page: http://www.simplesconsultoria.com.br
Author: Simples Consultoria
Author-email: products@simplesconsultoria.com.br
License: GPL
Keywords: contentrules action plone group
Platform: UNKNOWN
Classifier: Framework :: Plone
Classifier: Framework :: Zope2
Classifier: Framework :: Zope3
Classifier: Programming Language :: Python
Classifier: Topic :: Software Development :: Libraries :: Python Modules
